prometheus_dirsize_exporter/__init__.py
prometheus_dirsize_exporter/exporter.py
prometheus_dirsize_exporter/metrics.py
prometheus_dirsize_exporter-3.2.dist-info/LICENSE
prometheus_dirsize_exporter-3.2.dist-info/METADATA
prometheus_dirsize_exporter-3.2.dist-info/WHEEL
prometheus_dirsize_exporter-3.2.dist-info/entry_points.txt
prometheus_dirsize_exporter-3.2.dist-info/top_level.txt
prometheus_dirsize_exporter-3.2.dist-info/RECORD
