Metadata-Version: 2.1
Name: prometheus-dirsize-exporter
Version: 3.2
Author: yuvipanda
Author-email: yuvipanda@gmail.com
License: 3-BSD
License-File: LICENSE
Requires-Dist: prometheus-client
